pulumi_eks_ml/__init__.py
pulumi_eks_ml/eks/__init__.py
pulumi_eks_ml/eks/cluster.py
pulumi_eks_ml/eks/config.py
pulumi_eks_ml/eks/irsa.py
pulumi_eks_ml/eks/karpenter.py
pulumi_eks_ml/eks_addons/__init__.py
pulumi_eks_ml/eks_addons/alb_controller_addon.py
pulumi_eks_ml/eks_addons/ebs_csi_addon.py
pulumi_eks_ml/eks_addons/efs_csi_addon.py
pulumi_eks_ml/eks_addons/fluent_bit_addon.py
pulumi_eks_ml/eks_addons/metrics_server_addon.py
pulumi_eks_ml/eks_addons/nvidia_device_plugin_addon.py
pulumi_eks_ml/eks_addons/tailscale_subnet_router_addon.py
pulumi_eks_ml/eks_apps/__init__.py
pulumi_eks_ml/eks_apps/skypilot.py
pulumi_eks_ml/vpc/__init__.py
pulumi_eks_ml/vpc/core.py
pulumi_eks_ml/vpc/multi_region.py
pulumi_eks_ml/vpc/utils.py
pulumi_eks_ml-0.1.2.dist-info/WHEEL
pulumi_eks_ml-0.1.2.dist-info/METADATA
pulumi_eks_ml-0.1.2.dist-info/RECORD
