Metadata-Version: 2.3
Name: pulumi-eks-ml
Version: 0.1.2
Summary: Pulumi EKS ML Infrastructure
Requires-Dist: ipaddress>=1.0.23
Requires-Dist: passlib>=1.7.4
Requires-Dist: pulumi>=3.0.0,<4.0.0
Requires-Dist: pulumi-aws>=7.0.0,<8.0.0
Requires-Dist: pulumi-eks>=4.0.1
Requires-Dist: pulumi-kubernetes>=4.10.0
Requires-Dist: pulumi-random>=4.18.3
Requires-Dist: pyyaml>=6.0.2
Requires-Python: >=3.12
